build/lib/build/lib/build/lib/build/lib/hyperplan/__init__.py
build/lib/build/lib/build/lib/build/lib/hyperplan/algorithm.py
build/lib/build/lib/build/lib/build/lib/hyperplan/api.py
build/lib/build/lib/build/lib/build/lib/hyperplan/errors.py
build/lib/build/lib/build/lib/build/lib/hyperplan/feature_schema.py
build/lib/build/lib/build/lib/build/lib/hyperplan/features_descriptors.py
build/lib/build/lib/build/lib/build/lib/hyperplan/get_input.py
build/lib/build/lib/build/lib/build/lib/hyperplan/hpcmd.py
build/lib/build/lib/build/lib/build/lib/hyperplan/index.py
build/lib/build/lib/build/lib/build/lib/hyperplan/label_schema.py
build/lib/build/lib/build/lib/build/lib/hyperplan/labels_descriptors.py
build/lib/build/lib/build/lib/build/lib/hyperplan/predict.py
build/lib/build/lib/build/lib/build/lib/hyperplan/project.py
build/lib/build/lib/build/lib/build/lib/hyperplan/qcm_result.py
build/lib/build/lib/build/lib/build/lib/tests/__init__.py
build/lib/build/lib/build/lib/build/lib/tests/test_api.py
build/lib/build/lib/build/lib/hyperplan/__init__.py
build/lib/build/lib/build/lib/hyperplan/algorithm.py
build/lib/build/lib/build/lib/hyperplan/api.py
build/lib/build/lib/build/lib/hyperplan/errors.py
build/lib/build/lib/build/lib/hyperplan/feature_schema.py
build/lib/build/lib/build/lib/hyperplan/features_descriptors.py
build/lib/build/lib/build/lib/hyperplan/get_input.py
build/lib/build/lib/build/lib/hyperplan/hpcmd.py
build/lib/build/lib/build/lib/hyperplan/index.py
build/lib/build/lib/build/lib/hyperplan/label_schema.py
build/lib/build/lib/build/lib/hyperplan/labels_descriptors.py
build/lib/build/lib/build/lib/hyperplan/predict.py
build/lib/build/lib/build/lib/hyperplan/project.py
build/lib/build/lib/build/lib/hyperplan/qcm_result.py
build/lib/build/lib/build/lib/tests/__init__.py
build/lib/build/lib/build/lib/tests/test_api.py
build/lib/build/lib/hyperplan/__init__.py
build/lib/build/lib/hyperplan/algorithm.py
build/lib/build/lib/hyperplan/api.py
hyperplan_cli-0.0.1rc3.dist-info/LICENSE
hyperplan_cli-0.0.1rc3.dist-info/METADATA
hyperplan_cli-0.0.1rc3.dist-info/WHEEL
hyperplan_cli-0.0.1rc3.dist-info/entry_points.txt
hyperplan_cli-0.0.1rc3.dist-info/top_level.txt
hyperplan_cli-0.0.1rc3.dist-info/RECORD
