Metadata-Version: 2.1
Name: hyperplan-cli
Version: 0.0.1rc3
Summary: A Hyperplan cli tool to help you manage your Hyperplan server
Home-page: https://github.com/hyperplan/cli
Author: Antoine Sauray
Author-email: antoine@hyperplan.io
License: UNKNOWN
Platform: UNKNOWN
Classifier: Programming Language :: Python :: 3
Classifier: License :: OSI Approved :: MIT License
Classifier: Operating System :: OS Independent
Requires-Dist: keyring
Requires-Dist: prettytable
Requires-Dist: requests
